python_package_alexandro/__init__.py
python_package_alexandro/__main__.py
python_package_alexandro/collection.py
python_package_alexandro-0.0.2.dist-info/licenses/LICENSE
python_package_alexandro-0.0.2.dist-info/METADATA
python_package_alexandro-0.0.2.dist-info/WHEEL
python_package_alexandro-0.0.2.dist-info/top_level.txt
python_package_alexandro-0.0.2.dist-info/RECORD
