Metadata-Version: 2.4
Name: python_package_alexandro
Version: 0.0.2
Summary: Simple package
Author-email: Alexandro <logosua@ukr.net>
License: MIT
Project-URL: Homepage, https://github.com/Alexandro-khm
Project-URL: Issues, https://github.com/Alexandro-khm/issues
Classifier: Programming Language :: Python :: 3
Classifier: License :: OSI Approved :: MIT License
Classifier: Operating System :: OS Independent
Requires-Python: >=3.9
License-File: LICENSE
Dynamic: license-file
